adelin/Crypto_.py
adelin/DB_Tools.py
adelin/Filecheck.py
adelin/Object_.py
adelin/Readwrite.py
adelin/__init__.py
adelin-0.1.1.dist-info/LICENSE
adelin-0.1.1.dist-info/METADATA
adelin-0.1.1.dist-info/WHEEL
adelin-0.1.1.dist-info/top_level.txt
adelin-0.1.1.dist-info/RECORD
