Metadata-Version: 2.1
Name: adelin
Version: 0.1.1
Summary: simple database project
Author-email: "M.E.K" <info@adelin.com.tr>
Project-URL: Homepage, https://github.com/cypresspy/adelin
Project-URL: Bug Tracker, https://github.com/cypresspy/adelin
Classifier: Programming Language :: Python :: 3
Classifier: License :: OSI Approved :: MIT License
Classifier: Operating System :: OS Independent
Requires-Python: >=3.9
License-File: LICENSE
